.DS_Store
.coverage
.git/FETCH_HEAD
.git/HEAD
.git/config
.git/description
.git/hooks/applypatch-msg.sample
.git/hooks/commit-msg.sample
.git/hooks/fsmonitor-watchman.sample
.git/hooks/post-update.sample
.git/hooks/pre-applypatch.sample
.git/hooks/pre-commit.sample
.git/hooks/pre-merge-commit.sample
.git/hooks/pre-push.sample
.git/hooks/pre-rebase.sample
.git/hooks/pre-receive.sample
.git/hooks/prepare-commit-msg.sample
.git/hooks/push-to-checkout.sample
.git/hooks/sendemail-validate.sample
.git/hooks/update.sample
.git/index
.git/info/exclude
.git/logs/HEAD
.git/objects/00/304486e82972ddabfeb872c16f8b1ea8b7578b
.git/objects/00/3e530f4fd256fc806638dd96a2aeaecd27151a
.git/objects/04/a613de46292e0bcec7f7da22661952a805dd7c
.git/objects/07/1c809cff9cacde43a84605dc7a41a076f2e71c
.git/objects/08/bfb44f7c87ed269e2acc6b164d76654f36005b
.git/objects/0b/52a892e131d40c6d1f25fff25867ff16cf0c53
.git/objects/0c/1efc4adae193cb309352775cec6648baea0c2f
.git/objects/0f/2ec67ee8e6657ca3ea21a61560182a637ac1b3
.git/objects/11/42a9b5076cc3d522114583e683a82aeaaaedb0
.git/objects/13/813afb6002e79ff1c69043ae52cb561d96406a
.git/objects/16/bfa007539c89c0b2f12f83a430f1463162285d
.git/objects/18/e23a942445f74e639b846a10416e329ea3f4c4
.git/objects/20/a4a61e7aa7e98028b5d3d04015c4c5c9bcb8a3
.git/objects/24/24b19d3fa31f0b2b04b2f8fda1c9d3ac0179de
.git/objects/25/0f5665fa64b70c822190199b3b804b10f8b9d8
.git/objects/25/e49589cebe58a8ef05f188c4227ed80f73e8d9
.git/objects/2a/924f1d6a8bc930c5296bdb2d5c2d3e39b04a1c
.git/objects/2e/03e8da6162d35b91a32fa24b62f9b88ebde834
.git/objects/30/fee9d0f76a47aec5ef23e46adbf6bab4671eac
.git/objects/37/63124f0d744056989ae633428c596a534d9686
.git/objects/3d/101e5f0e8ce86d974d27ebaea1c2048f07f57e
.git/objects/40/52d06e45a3d7564b3052ca3e91b39f83288cec
.git/objects/45/3392ca713f03e2ee4d8329ba4e447387a32758
.git/objects/4e/cd5430713bb23428bba8621be701f1b1b3332e
.git/objects/50/dc774a71fdb6d0da833710f83a096f7f382987
.git/objects/51/7d0b29cb1193b1211c8853b58c65cddd1fa4d2
project_big_data.egg-info/PKG-INFO
project_big_data.egg-info/SOURCES.txt
project_big_data.egg-info/dependency_links.txt
project_big_data.egg-info/requires.txt
project_big_data.egg-info/top_level.txt
projet_kit_big_data-1.0.0.dist-info/METADATA
projet_kit_big_data-1.0.0.dist-info/WHEEL
projet_kit_big_data-1.0.0.dist-info/RECORD
