Metadata-Version: 2.1
Name: PROJET_KIT_BIG_DATA
Version: 1.0.0
Summary: ToDo list du projet kit big data
Author: Guillaume
Requires-Python: >=3.9,<3.13
Classifier: Programming Language :: Python :: 3
Classifier: Programming Language :: Python :: 3.9
Classifier: Programming Language :: Python :: 3.10
Classifier: Programming Language :: Python :: 3.11
Classifier: Programming Language :: Python :: 3.12
Requires-Dist: argparse (>=1.4.0,<2.0.0)
Requires-Dist: datetime (>=5.2,<6.0)
Requires-Dist: gradio (>=3.50.2,<4.0.0)
Requires-Dist: mongomock (>=4.1.2,<5.0.0)
Requires-Dist: numpy (>=1.26.1,<2.0.0)
Requires-Dist: pymongo (>=4.5.0,<5.0.0)
Requires-Dist: pytest (>=7.4.3,<8.0.0)
Requires-Dist: sphinx (>=7.2.6,<8.0.0)
Requires-Dist: uuid (>=1.30,<2.0)
